LICENSE.txt
MANIFEST.in
README.rst
bindings.i
constants.py
odroid_wiringpi.py
setup.cfg
setup.py
wiringpi-class.py
wiringpi.i
wiringpi_wrap.c
WiringPi/version.h
WiringPi/devLib/ds1302.c
WiringPi/devLib/ds1302.h
WiringPi/devLib/font.h
WiringPi/devLib/gertboard.c
WiringPi/devLib/gertboard.h
WiringPi/devLib/lcd.c
WiringPi/devLib/lcd.h
WiringPi/devLib/lcd128x64.c
WiringPi/devLib/lcd128x64.h
WiringPi/devLib/maxdetect.c
WiringPi/devLib/maxdetect.h
WiringPi/devLib/piFace.c
WiringPi/devLib/piFace.h
WiringPi/devLib/piGlow.c
WiringPi/devLib/piGlow.h
WiringPi/devLib/piNes.c
WiringPi/devLib/piNes.h
WiringPi/devLib/scrollPhat.c
WiringPi/devLib/scrollPhat.h
WiringPi/devLib/scrollPhatFont.h
WiringPi/examples/header.h
WiringPi/wiringPi/ads1115.c
WiringPi/wiringPi/ads1115.h
WiringPi/wiringPi/bmp180.c
WiringPi/wiringPi/bmp180.h
WiringPi/wiringPi/drcNet.c
WiringPi/wiringPi/drcNet.h
WiringPi/wiringPi/drcSerial.c
WiringPi/wiringPi/drcSerial.h
WiringPi/wiringPi/ds18b20.c
WiringPi/wiringPi/ds18b20.h
WiringPi/wiringPi/htu21d.c
WiringPi/wiringPi/htu21d.h
WiringPi/wiringPi/max31855.c
WiringPi/wiringPi/max31855.h
WiringPi/wiringPi/max5322.c
WiringPi/wiringPi/max5322.h
WiringPi/wiringPi/mcp23008.c
WiringPi/wiringPi/mcp23008.h
WiringPi/wiringPi/mcp23016.c
WiringPi/wiringPi/mcp23016.h
WiringPi/wiringPi/mcp23016reg.h
WiringPi/wiringPi/mcp23017.c
WiringPi/wiringPi/mcp23017.h
WiringPi/wiringPi/mcp23s08.c
WiringPi/wiringPi/mcp23s08.h
WiringPi/wiringPi/mcp23s17.c
WiringPi/wiringPi/mcp23s17.h
WiringPi/wiringPi/mcp23x08.h
WiringPi/wiringPi/mcp23x0817.h
WiringPi/wiringPi/mcp3002.c
WiringPi/wiringPi/mcp3002.h
WiringPi/wiringPi/mcp3004.c
WiringPi/wiringPi/mcp3004.h
WiringPi/wiringPi/mcp3422.c
WiringPi/wiringPi/mcp3422.h
WiringPi/wiringPi/mcp4802.c
WiringPi/wiringPi/mcp4802.h
WiringPi/wiringPi/odroid_template.h
WiringPi/wiringPi/odroidc1.c
WiringPi/wiringPi/odroidc1.h
WiringPi/wiringPi/odroidc2.c
WiringPi/wiringPi/odroidc2.h
WiringPi/wiringPi/odroidc4.c
WiringPi/wiringPi/odroidc4.h
odroid_wiringpi.egg-info/PKG-INFO
odroid_wiringpi.egg-info/SOURCES.txt
odroid_wiringpi.egg-info/dependency_links.txt
odroid_wiringpi.egg-info/top_level.txt
