Metadata-Version: 2.1
Name: odroid-wiringpi
Version: 3.17.1
Summary: A Port of WiringPi Python project for ODROID boards
Home-page: https://github.com/hardkernel/WiringPi2-Python
Author: Deokgyu Yang
Author-email: secugyu@gmail.com
License: LGPL
Platform: UNKNOWN
License-File: LICENSE.txt
